{
	"category" : "AutoTDD-GUI",
	"classinstvars" : [
		 ],
	"classvars" : [
		 ],
	"commentStamp" : "be 7/25/2019 10:00",
	"instvars" : [
		"categories",
		"testCategories",
		"categoryClasses",
		"categoryPattern",
		"testCategoryClasses",
		"selectedCategory",
		"selectedCategories",
		"selectedCategoryClasses",
		"selectedTestCategory",
		"selectedTestCategories",
		"selectedTestCategoryClasses",
		"classwiseCategorySelection",
		"classwiseTestCategorySelection",
		"localTesting",
		"travisTesting" ],
	"name" : "ATDDWatcherEditor",
	"pools" : [
		 ],
	"super" : "ATDDEditor",
	"type" : "normal" }
